skferm/__init__.py
skferm/hello.py
skferm/data/__init__.py
skferm/data/rheolaser_export.csv.gz
skferm/datasets/__init__.py
skferm/datasets/rheolaser.py
skferm/datasets/synthetic.py
skferm/growth_models/__init__.py
skferm/growth_models/gompertz.py
skferm/growth_models/logistic.py
skferm/smoothing/__init__.py
skferm/smoothing/moving_average.py
skferm/smoothing/pipe.py
skferm/smoothing/savgol_filter.py
skferm/smoothing/spline.py
scikit_ferm-0.1.1.dist-info/METADATA
scikit_ferm-0.1.1.dist-info/WHEEL
scikit_ferm-0.1.1.dist-info/licenses/LICENSE
scikit_ferm-0.1.1.dist-info/RECORD
