Metadata-Version: 2.4
Name: scikit-ferm
Version: 0.1.1
Summary: A scikit-learn compatible package for fermentations.
Project-URL: Homepage, https://aschwins.github.io/scikit-ferm/
Project-URL: Issues, https://github.com/Aschwins/scikit-ferm/issues
Author-email: Aschwin Schilperoort <author@example.com>
License-Expression: Apache-2.0
License-File: LICENSE
Keywords: acidification,fermentation,python,scikit-ferm
Classifier: Operating System :: OS Independent
Classifier: Programming Language :: Python :: 3
Requires-Python: >=3.12
Requires-Dist: numpy>=2.2.2
Requires-Dist: pandas>=2.2.3
Requires-Dist: scikit-learn>=1.6.1
